psina228/__init__.py
psina228/installer.py
psina228/version.py
psina228-1.0.0.dist-info/licenses/LICENSE
psina228-1.0.0.dist-info/METADATA
psina228-1.0.0.dist-info/WHEEL
psina228-1.0.0.dist-info/entry_points.txt
psina228-1.0.0.dist-info/top_level.txt
psina228-1.0.0.dist-info/RECORD
